dagster/__init__.py
dagster/__main__.py
dagster/builtins.py
dagster/logzample.py
dagster/primitive_mapping.py
dagster/version.py
dagster/api/__init__.py
dagster/api/get_server_id.py
dagster/api/list_repositories.py
dagster/api/notebook_data.py
dagster/api/snapshot_execution_plan.py
dagster/api/snapshot_partition.py
dagster/api/snapshot_pipeline.py
dagster/api/snapshot_repository.py
dagster/api/snapshot_schedule.py
dagster/api/snapshot_sensor.py
dagster/check/README.md
dagster/check/__init__.py
dagster/cli/__init__.py
dagster/cli/api.py
dagster/cli/asset.py
dagster/cli/config_scaffolder.py
dagster/cli/debug.py
dagster/cli/instance.py
dagster/cli/load_handle.py
dagster/cli/new_project.py
dagster/cli/pipeline.py
dagster/cli/run.py
dagster/cli/schedule.py
dagster/cli/sensor.py
dagster/cli/workspace/__init__.py
dagster/cli/workspace/cli_target.py
dagster/config/__init__.py
dagster/config/config_schema.py
dagster/config/config_type.py
dagster/config/errors.py
dagster/config/evaluate_value_result.py
dagster/config/field.py
dagster/config/field_utils.py
dagster/config/iterate_types.py
dagster/config/post_process.py
dagster/config/run_config.py
dagster/config/snap.py
dagster/config/source.py
dagster/config/stack.py
dagster/config/traversal_context.py
dagster/config/type_printer.py
dagster/config/validate.py
dagster/core/__init__.py
dagster/core/assets.py
dagster/core/code_pointer.py
dagster/core/debug.py
dagster/core/decorator_utils.py
dagster/core/errors.py
dagster/core/log_manager.py
dagster/core/origin.py
dagster/core/telemetry.py
dagster/core/test_utils.py
dagster/core/utility_solids.py
dagster/core/utils.py
dagster/core/asset_defs/__init__.py
dagster/core/asset_defs/asset_in.py
dagster/core/asset_defs/assets_job.py
dagster/core/asset_defs/decorators.py
dagster/core/asset_defs/foreign_asset.py
dagster/core/definitions/__init__.py
dagster/core/definitions/composition.py
dagster/core/definitions/config.py
dagster/core/definitions/configurable.py
dagster_custom-0.12.14.dist-info/LICENSE
dagster_custom-0.12.14.dist-info/METADATA
dagster_custom-0.12.14.dist-info/WHEEL
dagster_custom-0.12.14.dist-info/entry_points.txt
dagster_custom-0.12.14.dist-info/top_level.txt
dagster_custom-0.12.14.dist-info/RECORD
