Metadata-Version: 2.1
Name: dagster-custom
Version: 0.12.14
Summary: A data orchestrator for machine learning, analytics, and ETL.
Home-page: https://github.com/dagster-io/dagster
Author: Elementl
Author-email: hello@elementl.com
License: Apache-2.0
Platform: UNKNOWN
Classifier: Programming Language :: Python :: 3.6
Classifier: Programming Language :: Python :: 3.7
Classifier: Programming Language :: Python :: 3.8
Classifier: License :: OSI Approved :: Apache Software License
Classifier: Operating System :: OS Independent
Requires-Dist: ipython-genutils (==0.2.0)
Requires-Dist: graphene (==2.1.9)
Requires-Dist: graphql-core (==2.3.2)
Requires-Dist: graphql-relay (==2.0.1)
Requires-Dist: graphql-server-core (==1.2.0)
Requires-Dist: graphql-ws (==0.3.1)
Requires-Dist: click (<9.0,>=5.0)
Requires-Dist: coloredlogs (<=14.0,>=6.1)
Requires-Dist: Jinja2 (<3.0)
Requires-Dist: PyYAML (>=5.1)
Requires-Dist: MarkupSafe (==1.1.1)
Requires-Dist: itsdangerous (==1.1.0)
Requires-Dist: alembic (!=1.6.3,<1.7.0,>=1.2.1)
Requires-Dist: croniter (>=0.3.34)
Requires-Dist: grpcio (>=1.32.0)
Requires-Dist: grpcio-health-checking (>=1.32.0)
Requires-Dist: packaging (>=20.9)
Requires-Dist: pendulum
Requires-Dist: protobuf (>=3.20.*)
Requires-Dist: python-dateutil
Requires-Dist: pytz
Requires-Dist: rx (<2,>=1.6)
Requires-Dist: tabulate
Requires-Dist: tqdm
Requires-Dist: typing-compat
Requires-Dist: sqlalchemy (>=1.0)
Requires-Dist: toposort (>=1.0)
Requires-Dist: watchdog (>=0.8.3)
Requires-Dist: docstring-parser
Requires-Dist: psutil (>=1.0) ; platform_system == "Windows"
Requires-Dist: pywin32 (!=226) ; platform_system == "Windows"
Provides-Extra: docker
Requires-Dist: docker ; extra == 'docker'
Provides-Extra: test
Requires-Dist: astroid (<2.5,>=2.3.3) ; extra == 'test'
Requires-Dist: ipython-genutils (==0.2.0) ; extra == 'test'
Requires-Dist: black (==20.8b1) ; extra == 'test'
Requires-Dist: graphene (==2.1.9) ; extra == 'test'
Requires-Dist: graphql-core (==2.3.2) ; extra == 'test'
Requires-Dist: graphql-relay (==2.0.1) ; extra == 'test'
Requires-Dist: graphql-server-core (==1.2.0) ; extra == 'test'
Requires-Dist: graphql-ws (==0.3.1) ; extra == 'test'
Requires-Dist: coverage (==5.3) ; extra == 'test'
Requires-Dist: docker ; extra == 'test'
Requires-Dist: MarkupSafe (==1.1.1) ; extra == 'test'
Requires-Dist: itsdangerous (==1.1.0) ; extra == 'test'
Requires-Dist: flake8 (>=3.7.8) ; extra == 'test'
Requires-Dist: freezegun (>=0.3.15) ; extra == 'test'
Requires-Dist: grpcio-tools (==1.32.0) ; extra == 'test'
Requires-Dist: isort (<5,>=4.3.21) ; extra == 'test'
Requires-Dist: mock (==3.0.5) ; extra == 'test'
Requires-Dist: protobuf (>=3.20.*) ; extra == 'test'
Requires-Dist: pylint (==2.6.0) ; extra == 'test'
Requires-Dist: pytest-cov (==2.10.1) ; extra == 'test'
Requires-Dist: pytest-dependency (==0.5.1) ; extra == 'test'
Requires-Dist: pytest-mock (==3.3.1) ; extra == 'test'
Requires-Dist: pytest-rerunfailures (==10.0) ; extra == 'test'
Requires-Dist: pytest-runner (==5.2) ; extra == 'test'
Requires-Dist: pytest-xdist (==2.1.0) ; extra == 'test'
Requires-Dist: pytest (==6.1.1) ; extra == 'test'
Requires-Dist: responses (==0.10.*) ; extra == 'test'
Requires-Dist: snapshottest (==0.6.0) ; extra == 'test'
Requires-Dist: tox (==3.14.2) ; extra == 'test'
Requires-Dist: tox-pip-version (==0.0.7) ; extra == 'test'
Requires-Dist: tqdm (==4.48.0) ; extra == 'test'
Requires-Dist: yamllint ; extra == 'test'
